pyrust_poker-0.2.3.dist-info/METADATA
pyrust_poker-0.2.3.dist-info/WHEEL
pyrust_poker-0.2.3.dist-info/licenses/LICENSE
pyrust_poker/get_hand_strengths.py
pyrust_poker/__init__.py
pyrust_poker/pyrust_poker.cpython-312-x86_64-linux-gnu.so
pyrust_poker-0.2.3.dist-info/RECORD
