Metadata-Version: 2.4
Name: pyrust_poker
Version: 0.2.3
Classifier: Programming Language :: Rust
Classifier: Programming Language :: Python :: Implementation :: CPython
Classifier: Programming Language :: Python :: Implementation :: PyPy
License-File: LICENSE
Summary: Rust poker library
Keywords: poker,python
Author: kmurf1999 <kwmurph2@asu.edu>
Author-email: kmurf1999 <kwmurph2@asu.edu>
License: MIT
Requires-Python: >=3.8
Project-URL: Source Code, https://github.com/Townsheriff/python_rust_poker
